<?xml version="1.0" encoding="UTF-8"?>
<!DOCTYPE mapper PUBLIC "-//mybatis.org//DTD Mapper 3.0//EN" "http://mybatis.org/dtd/mybatis-3-mapper.dtd">
<mapper namespace="com.xhp.crowdfunding.dao.HomecarouselMapper">
  <resultMap id="BaseResultMap" type="com.xhp.crowdfunding.entity.Homecarousel">
    <!--
      WARNING - @mbg.generated
      This element is automatically generated by MyBatis Generator, do not modify.
    -->
    <id column="HCid" jdbcType="VARCHAR" property="hcid" />
    <result column="HCimage" jdbcType="VARCHAR" property="hcimage" />
  </resultMap>
  <sql id="Base_Column_List">
    <!--
      WARNING - @mbg.generated
      This element is automatically generated by MyBatis Generator, do not modify.
    -->
    HCid, HCimage
  </sql>
  <select id="selectByPrimaryKey" parameterType="java.lang.String" resultMap="BaseResultMap">
    <!--
      WARNING - @mbg.generated
      This element is automatically generated by MyBatis Generator, do not modify.
    -->
    select 
    <include refid="Base_Column_List" />
    from homecarousel
    where HCid = #{hcid,jdbcType=VARCHAR}
  </select>
  <delete id="deleteByPrimaryKey" parameterType="java.lang.String">
    <!--
      WARNING - @mbg.generated
      This element is automatically generated by MyBatis Generator, do not modify.
    -->
    delete from homecarousel
    where HCid = #{hcid,jdbcType=VARCHAR}
  </delete>
  <insert id="insert" parameterType="com.xhp.crowdfunding.entity.Homecarousel">
    <!--
      WARNING - @mbg.generated
      This element is automatically generated by MyBatis Generator, do not modify.
    -->
    insert into homecarousel (HCid, HCimage)
    values (#{hcid,jdbcType=VARCHAR}, #{hcimage,jdbcType=VARCHAR})
  </insert>
  <insert id="insertSelective" parameterType="com.xhp.crowdfunding.entity.Homecarousel">
    <!--
      WARNING - @mbg.generated
      This element is automatically generated by MyBatis Generator, do not modify.
    -->
    insert into homecarousel
    <trim prefix="(" suffix=")" suffixOverrides=",">
      <if test="hcid != null">
        HCid,
      </if>
      <if test="hcimage != null">
        HCimage,
      </if>
    </trim>
    <trim prefix="values (" suffix=")" suffixOverrides=",">
      <if test="hcid != null">
        #{hcid,jdbcType=VARCHAR},
      </if>
      <if test="hcimage != null">
        #{hcimage,jdbcType=VARCHAR},
      </if>
    </trim>
  </insert>
  <update id="updateByPrimaryKeySelective" parameterType="com.xhp.crowdfunding.entity.Homecarousel">
    <!--
      WARNING - @mbg.generated
      This element is automatically generated by MyBatis Generator, do not modify.
    -->
    update homecarousel
    <set>
      <if test="hcimage != null">
        HCimage = #{hcimage,jdbcType=VARCHAR},
      </if>
    </set>
    where HCid = #{hcid,jdbcType=VARCHAR}
  </update>
  <update id="updateByPrimaryKey" parameterType="com.xhp.crowdfunding.entity.Homecarousel">
    <!--
      WARNING - @mbg.generated
      This element is automatically generated by MyBatis Generator, do not modify.
    -->
    update homecarousel
    set HCimage = #{hcimage,jdbcType=VARCHAR}
    where HCid = #{hcid,jdbcType=VARCHAR}
  </update>
</mapper>